Workbook

Sheet Sales 2023
A1: Date | B1: Year | C1: Month | D1: Product | E1: Region | F1: Units_Sold | G1: Unit_Price | H1: Revenue | I1: Profit
A2: 44927 | B2: 2023 | C2: January | D2: Laptop | E2: Accra | F2: 186 | G2: 1318 | H2: 245148 | I2: 31260
A3: 44927 | B3: 2023 | C3: January | D3: Laptop | E3: Kumasi | F3: 154 | G3: 1259 | H3: 193886 | I3: 23926
A4: 44927 | B4: 2023 | C4: January | D4: Laptop | E4: Takoradi | F4: 301 | G4: 1097 | H4: 330197 | I4: 75921
A5: 44927 | B5: 2023 | C5: January | D5: Laptop | E5: Tamale | F5: 183 | G5: 1122 | H5: 205326 | I5: 40579
A6: 44927 | B6: 2023 | C6: January | D6: Laptop | E6: Cape Coast | F6: 397 | G6: 1370 | H6: 543890 | I6: 122302
A7: 44927 | B7: 2023 | C7: January | D7: Smartphone | E7: Accra | F7: 382 | G7: 720 | H7: 275040 | I7: 68438
A8: 44927 | B8: 2023 | C8: January | D8: Smartphone | E8: Kumasi | F8: 245 | G8: 780 | H8: 191100 | I8: 34152
A9: 44927 | B9: 2023 | C9: January | D9: Smartphone | E9: Takoradi | F9: 322 | G9: 724 | H9: 233128 | I9: 41663
A10: 44927 | B10: 2023 | C10: January | D10: Smartphone | E10: Tamale | F10: 255 | G10: 729 | H10: 185895 | I10: 45741
A11: 44927 | B11: 2023 | C11: January | D11: Smartphone | E11: Cape Coast | F11: 358 | G11: 811 | H11: 290338 | I11: 63228
A12: 44927 | B12: 2023 | C12: January | D12: Headphones | E12: Accra | F12: 133 | G12: 119 | H12: 15827 | I12: 3916
A13: 44927 | B13: 2023 | C13: January | D13: Headphones | E13: Kumasi | F13: 215 | G13: 133 | H13: 28595 | I13: 5777
... A361: 45261 | B361: 2023 | C361: December | D361: Monitor | E361: Cape Coast | F361: 228 | G361: 381 | H361: 86868 | I361: 18122

Sheet Sales 2024
A1: Date | B1: Year | C1: Month | D1: Product | E1: Region | F1: Units_Sold | G1: Unit_Price | H1: Revenue | I1: Profit
A2: 45292 | B2: 2024 | C2: January | D2: Laptop | E2: Accra | F2: 323 | G2: 1154 | H2: 372742 | I2: 64638
A3: 45292 | B3: 2024 | C3: January | D3: Laptop | E3: Kumasi | F3: 257 | G3: 1287 | H3: 330759 | I3: 35635
A4: 45292 | B4: 2024 | C4: January | D4: Laptop | E4: Takoradi | F4: 121 | G4: 1091 | H4: 132011 | I4: 27172
A5: 45292 | B5: 2024 | C5: January | D5: Laptop | E5: Tamale | F5: 322 | G5: 1379 | H5: 444038 | I5: 81423
A6: 45292 | B6: 2024 | C6: January | D6: Laptop | E6: Cape Coast | F6: 191 | G6: 1354 | H6: 258614 | I6: 27178
A7: 45292 | B7: 2024 | C7: January | D7: Smartphone | E7: Accra | F7: 227 | G7: 866 | H7: 196582 | I7: 25337
A8: 45292 | B8: 2024 | C8: January | D8: Smartphone | E8: Kumasi | F8: 457 | G8: 908 | H8: 414956 | I8: 71012
A9: 45292 | B9: 2024 | C9: January | D9: Smartphone | E9: Takoradi | F9: 211 | G9: 727 | H9: 153397 | I9: 29059
A10: 45292 | B10: 2024 | C10: January | D10: Smartphone | E10: Tamale | F10: 216 | G10: 744 | H10: 160704 | I10: 17925
A11: 45292 | B11: 2024 | C11: January | D11: Smartphone | E11: Cape Coast | F11: 431 | G11: 826 | H11: 356006 | I11: 59152
A12: 45292 | B12: 2024 | C12: January | D12: Headphones | E12: Accra | F12: 136 | G12: 117 | H12: 15912 | I12: 2878
A13: 45292 | B13: 2024 | C13: January | D13: Headphones | E13: Kumasi | F13: 335 | G13: 123 | H13: 41205 | I13: 6758
... A361: 45627 | B361: 2024 | C361: December | D361: Monitor | E361: Cape Coast | F361: 251 | G361: 392 | H361: 98392 | I361: 15646

Sheet All Data
A1: Date | B1: Year | C1: Month | D1: Product | E1: Region | F1: Units_Sold | G1: Unit_Price | H1: Revenue | I1: Profit
A2: 44927 | B2: 2023 | C2: January | D2: Laptop | E2: Accra | F2: 186 | G2: 1318 | H2: 245148 | I2: 31260
A3: 44927 | B3: 2023 | C3: January | D3: Laptop | E3: Kumasi | F3: 154 | G3: 1259 | H3: 193886 | I3: 23926
A4: 44927 | B4: 2023 | C4: January | D4: Laptop | E4: Takoradi | F4: 301 | G4: 1097 | H4: 330197 | I4: 75921
A5: 44927 | B5: 2023 | C5: January | D5: Laptop | E5: Tamale | F5: 183 | G5: 1122 | H5: 205326 | I5: 40579
A6: 44927 | B6: 2023 | C6: January | D6: Laptop | E6: Cape Coast | F6: 397 | G6: 1370 | H6: 543890 | I6: 122302
A7: 44927 | B7: 2023 | C7: January | D7: Smartphone | E7: Accra | F7: 382 | G7: 720 | H7: 275040 | I7: 68438
A8: 44927 | B8: 2023 | C8: January | D8: Smartphone | E8: Kumasi | F8: 245 | G8: 780 | H8: 191100 | I8: 34152
A9: 44927 | B9: 2023 | C9: January | D9: Smartphone | E9: Takoradi | F9: 322 | G9: 724 | H9: 233128 | I9: 41663
A10: 44927 | B10: 2023 | C10: January | D10: Smartphone | E10: Tamale | F10: 255 | G10: 729 | H10: 185895 | I10: 45741
A11: 44927 | B11: 2023 | C11: January | D11: Smartphone | E11: Cape Coast | F11: 358 | G11: 811 | H11: 290338 | I11: 63228
A12: 44927 | B12: 2023 | C12: January | D12: Headphones | E12: Accra | F12: 133 | G12: 119 | H12: 15827 | I12: 3916
A13: 44927 | B13: 2023 | C13: January | D13: Headphones | E13: Kumasi | F13: 215 | G13: 133 | H13: 28595 | I13: 5777
... A721: 45627 | B721: 2024 | C721: December | D721: Monitor | E721: Cape Coast | F721: 251 | G721: 392 | H721: 98392 | I721: 15646

Sheet Dashboard
A1: Sales Performance Dashboard (2023–2024)
A2: Prepared by Emmanuel Nyamekye | Data Analyst
A4: KPI | B4: Value
A5: Total Revenue (2023) | B5: =SUMIFS('All Data'!H:H,'All Data'!B:B,2023) -> 0
A6: Total Revenue (2024) | B6: =SUMIFS('All Data'!H:H,'All Data'!B:B,2024) -> 0
A7: YoY Revenue Growth | B7: =(B6-B5)/IF(B5=0,1,B5) -> 0
A8: Total Profit (2024) | B8: =SUMIFS('All Data'!I:I,'All Data'!B:B,2024) -> 0
A9: Total Units Sold (2024) | B9: =SUMIFS('All Data'!F:F,'All Data'!B:B,2024) -> 0
A12: Month | B12: Revenue 2023 | C12: Revenue 2024
A13: January | B13: =SUMIFS('All Data'!H:H,'All Data'!B:B,2023,'All Data'!C:C,"January") -> 0 | C13: =SUMIFS('All Data'!H:H,'All Data'!B:B,2024,'All Data'!C:C,"January") -> 0
A14: February | B14: =SUMIFS('All Data'!H:H,'All Data'!B:B,2023,'All Data'!C:C,"February") -> 0 | C14: =SUMIFS('All Data'!H:H,'All Data'!B:B,2024,'All Data'!C:C,"February") -> 0
A15: March | B15: =SUMIFS('All Data'!H:H,'All Data'!B:B,2023,'All Data'!C:C,"March") -> 0 | C15: =SUMIFS('All Data'!H:H,'All Data'!B:B,2024,'All Data'!C:C,"March") -> 0
A16: April | B16: =SUMIFS('All Data'!H:H,'All Data'!B:B,2023,'All Data'!C:C,"April") -> 0 | C16: =SUMIFS('All Data'!H:H,'All Data'!B:B,2024,'All Data'!C:C,"April") -> 0
A17: May | B17: =SUMIFS('All Data'!H:H,'All Data'!B:B,2023,'All Data'!C:C,"May") -> 0 | C17: =SUMIFS('All Data'!H:H,'All Data'!B:B,2024,'All Data'!C:C,"May") -> 0
A18: June | B18: =SUMIFS('All Data'!H:H,'All Data'!B:B,2023,'All Data'!C:C,"June") -> 0 | C18: =SUMIFS('All Data'!H:H,'All Data'!B:B,2024,'All Data'!C:C,"June") -> 0
A19: July | B19: =SUMIFS('All Data'!H:H,'All Data'!B:B,2023,'All Data'!C:C,"July") -> 0 | C19: =SUMIFS('All Data'!H:H,'All Data'!B:B,2024,'All Data'!C:C,"July") -> 0
A20: August | B20: =SUMIFS('All Data'!H:H,'All Data'!B:B,2023,'All Data'!C:C,"August") -> 0 | C20: =SUMIFS('All Data'!H:H,'All Data'!B:B,2024,'All Data'!C:C,"August") -> 0
A21: September | B21: =SUMIFS('All Data'!H:H,'All Data'!B:B,2023,'All Data'!C:C,"September") -> 0 | C21: =SUMIFS('All Data'!H:H,'All Data'!B:B,2024,'All Data'!C:C,"September") -> 0
A22: October | B22: =SUMIFS('All Data'!H:H,'All Data'!B:B,2023,'All Data'!C:C,"October") -> 0 | C22: =SUMIFS('All Data'!H:H,'All Data'!B:B,2024,'All Data'!C:C,"October") -> 0
A23: November | B23: =SUMIFS('All Data'!H:H,'All Data'!B:B,2023,'All Data'!C:C,"November") -> 0 | C23: =SUMIFS('All Data'!H:H,'All Data'!B:B,2024,'All Data'!C:C,"November") -> 0
A24: December | B24: =SUMIFS('All Data'!H:H,'All Data'!B:B,2023,'All Data'!C:C,"December") -> 0 | C24: =SUMIFS('All Data'!H:H,'All Data'!B:B,2024,'All Data'!C:C,"December") -> 0
A26: Laptop | B26: =SUMIFS('All Data'!H:H,'All Data'!D:D,"Laptop",'All Data'!B:B,2024) -> 0
A27: Smartphone | B27: =SUMIFS('All Data'!H:H,'All Data'!D:D,"Smartphone",'All Data'!B:B,2024) -> 0
A28: Headphones | B28: =SUMIFS('All Data'!H:H,'All Data'!D:D,"Headphones",'All Data'!B:B,2024) -> 0
A29: Tablet | B29: =SUMIFS('All Data'!H:H,'All Data'!D:D,"Tablet",'All Data'!B:B,2024) -> 0
A30: Smartwatch | B30: =SUMIFS('All Data'!H:H,'All Data'!D:D,"Smartwatch",'All Data'!B:B,2024) -> 0
A31: Monitor | B31: =SUMIFS('All Data'!H:H,'All Data'!D:D,"Monitor",'All Data'!B:B,2024) -> 0
A34: Accra | B34: =SUMIFS('All Data'!H:H,'All Data'!E:E,"Accra",'All Data'!B:B,2024) -> 0
A35: Kumasi | B35: =SUMIFS('All Data'!H:H,'All Data'!E:E,"Kumasi",'All Data'!B:B,2024) -> 0
A36: Takoradi | B36: =SUMIFS('All Data'!H:H,'All Data'!E:E,"Takoradi",'All Data'!B:B,2024) -> 0
A37: Tamale | B37: =SUMIFS('All Data'!H:H,'All Data'!E:E,"Tamale",'All Data'!B:B,2024) -> 0
A38: Cape Coast | B38: =SUMIFS('All Data'!H:H,'All Data'!E:E,"Cape Coast",'All Data'!B:B,2024) -> 0
